insightlog/__init__.py
insightlog/config.py
insightlog/filters.py
insightlog/formatter.py
insightlog/logger.py
insightlog/sinks.py
insightlog/utils.py
insightlog101-0.1.14.dist-info/METADATA
insightlog101-0.1.14.dist-info/WHEEL
insightlog101-0.1.14.dist-info/top_level.txt
insightlog101-0.1.14.dist-info/RECORD
