Metadata-Version: 2.4
Name: insightlog101
Version: 0.1.14
Summary: Secure, redactable, context-aware logger for security and DevOps workflows.
Home-page: https://github.com/kmukoo101/insightlog
Author: kmukoo101
Author-email: kmukoo101 <you@example.com>
License: MIT
Project-URL: Homepage, https://github.com/kmukoo101/insightlog
Project-URL: Documentation, https://github.com/kmukoo101/insightlog/wiki
Project-URL: Source, https://github.com/kmukoo101/insightlog
Project-URL: Issues, https://github.com/kmukoo101/insightlog/issues
Project-URL: GitHub, https://github.com/kmukoo101/insightlog101
Classifier: Programming Language :: Python :: 3
Classifier: License :: OSI Approved :: MIT License
Classifier: Operating System :: OS Independent
Classifier: Intended Audience :: Developers
Classifier: Topic :: Security
Classifier: Topic :: Software Development :: Libraries :: Python Modules
Requires-Python: >=3.7
Requires-Dist: colorama>=0.4.6
Requires-Dist: PyYAML>=6.0
Requires-Dist: cryptography>=41.0.0
Dynamic: author
Dynamic: home-page
Dynamic: requires-python
